<?xml version="1.0" encoding="utf-8"?>
<cTrackSectionBlueprint>
	<Element>
		<Value>
			<Attribute name="DisplayName">
				<Localisation-cUserLocalisedString>
					<Element>
						<Value>
							<Attribute name="English">
								<cDeltaString>
									<Element>
										<Value>Maglev Beam</Value>
									</Element>
								</cDeltaString>
							</Attribute>
							<Attribute name="French">
								<cDeltaString>
									<Element>
										<Value />
									</Element>
								</cDeltaString>
							</Attribute>
							<Attribute name="Italian">
								<cDeltaString>
									<Element>
										<Value />
									</Element>
								</cDeltaString>
							</Attribute>
							<Attribute name="German">
								<cDeltaString>
									<Element>
										<Value />
									</Element>
								</cDeltaString>
							</Attribute>
							<Attribute name="Spanish">
								<cDeltaString>
									<Element>
										<Value />
									</Element>
								</cDeltaString>
							</Attribute>
							<Attribute name="Dutch">
								<cDeltaString>
									<Element>
										<Value />
									</Element>
								</cDeltaString>
							</Attribute>
							<Attribute name="Polish">
								<cDeltaString>
									<Element>
										<Value />
									</Element>
								</cDeltaString>
							</Attribute>
							<Attribute name="Russian">
								<cDeltaString>
									<Element>
										<Value />
									</Element>
								</cDeltaString>
							</Attribute>
							<Attribute name="Other">
								<__Indexed__Localisation-cUserLocalisedString-cOtherStringLangPair>
									<Element>
										<Value />
									</Element>
								</__Indexed__Localisation-cUserLocalisedString-cOtherStringLangPair>
							</Attribute>
							<Attribute name="Key">
								<cDeltaString>
									<Element>
										<Value />
									</Element>
								</cDeltaString>
							</Attribute>
						</Value>
					</Element>
				</Localisation-cUserLocalisedString>
			</Attribute>
			<Attribute name="EditorGroundOffset">
				<sFloat32>
					<Element>
						<Value>1</Value>
					</Element>
				</sFloat32>
			</Attribute>
			<Attribute name="isTunnel">
				<bool>
					<Element>
						<Value>0</Value>
					</Element>
				</bool>
			</Attribute>
			<Attribute name="Render">
				<cSectionRenderBlueprint>
					<Element>
						<Value>
							<Attribute name="CrossSectionID">
								<cDeltaString>
									<Element>
										<Value>RailNetwork\Track\Maglev Beam</Value>
									</Element>
								</cDeltaString>
							</Attribute>
							<Attribute name="CrossSectionCapID">
								<cDeltaString>
									<Element>
										<Value>RailNetwork\Track\Maglev Beam</Value>
									</Element>
								</cDeltaString>
							</Attribute>
							<Attribute name="CrossSectionWidth">
								<sFloat32>
									<Element>
										<Value>0</Value>
									</Element>
								</sFloat32>
							</Attribute>
							<Attribute name="CrossSectionHeight">
								<sFloat32>
									<Element>
										<Value>0</Value>
									</Element>
								</sFloat32>
							</Attribute>
							<Attribute name="CatenaryID">
								<cDeltaString>
									<Element>
										<Value />
									</Element>
								</cDeltaString>
							</Attribute>
							<Attribute name="StartGeometryBPID">
								<iBlueprintLibrary-cAbsoluteBlueprintID>
									<Element>
										<Value>
											<Attribute name="BlueprintSetID">
												<iBlueprintLibrary-cBlueprintSetID>
													<Element>
														<Value>
															<Attribute name="Provider">
																<cDeltaString>
																	<Element>
																		<Value />
																	</Element>
																</cDeltaString>
															</Attribute>
															<Attribute name="Product">
																<cDeltaString>
																	<Element>
																		<Value />
																	</Element>
																</cDeltaString>
															</Attribute>
														</Value>
													</Element>
												</iBlueprintLibrary-cBlueprintSetID>
											</Attribute>
											<Attribute name="BlueprintID">
												<cDeltaString>
													<Element>
														<Value />
													</Element>
												</cDeltaString>
											</Attribute>
										</Value>
									</Element>
								</iBlueprintLibrary-cAbsoluteBlueprintID>
							</Attribute>
							<Attribute name="MiddleGeometryBPID">
								<iBlueprintLibrary-cAbsoluteBlueprintID>
									<Element>
										<Value>
											<Attribute name="BlueprintSetID">
												<iBlueprintLibrary-cBlueprintSetID>
													<Element>
														<Value>
															<Attribute name="Provider">
																<cDeltaString>
																	<Element>
																		<Value />
																	</Element>
																</cDeltaString>
															</Attribute>
															<Attribute name="Product">
																<cDeltaString>
																	<Element>
																		<Value />
																	</Element>
																</cDeltaString>
															</Attribute>
														</Value>
													</Element>
												</iBlueprintLibrary-cBlueprintSetID>
											</Attribute>
											<Attribute name="BlueprintID">
												<cDeltaString>
													<Element>
														<Value />
													</Element>
												</cDeltaString>
											</Attribute>
										</Value>
									</Element>
								</iBlueprintLibrary-cAbsoluteBlueprintID>
							</Attribute>
							<Attribute name="EndGeometryBPID">
								<iBlueprintLibrary-cAbsoluteBlueprintID>
									<Element>
										<Value>
											<Attribute name="BlueprintSetID">
												<iBlueprintLibrary-cBlueprintSetID>
													<Element>
														<Value>
															<Attribute name="Provider">
																<cDeltaString>
																	<Element>
																		<Value />
																	</Element>
																</cDeltaString>
															</Attribute>
															<Attribute name="Product">
																<cDeltaString>
																	<Element>
																		<Value />
																	</Element>
																</cDeltaString>
															</Attribute>
														</Value>
													</Element>
												</iBlueprintLibrary-cBlueprintSetID>
											</Attribute>
											<Attribute name="BlueprintID">
												<cDeltaString>
													<Element>
														<Value />
													</Element>
												</cDeltaString>
											</Attribute>
										</Value>
									</Element>
								</iBlueprintLibrary-cAbsoluteBlueprintID>
							</Attribute>
							<Attribute name="RotateEndGeometry">
								<eBoolean>
									<Element>
										<Value>eTrue</Value>
									</Element>
								</eBoolean>
							</Attribute>
							<Attribute name="PopulationFrequency">
								<sFloat32>
									<Element>
										<Value>0</Value>
									</Element>
								</sFloat32>
							</Attribute>
							<Attribute name="ProfileMatchesPopulation">
								<eBoolean>
									<Element>
										<Value>eFalse</Value>
									</Element>
								</eBoolean>
							</Attribute>
							<Attribute name="LeftOffset">
								<sFloat32>
									<Element>
										<Value>0</Value>
									</Element>
								</sFloat32>
							</Attribute>
							<Attribute name="RightOffset">
								<sFloat32>
									<Element>
										<Value>0</Value>
									</Element>
								</sFloat32>
							</Attribute>
							<Attribute name="CapIfSectionTypeChange">
								<eBoolean>
									<Element>
										<Value>eFalse</Value>
									</Element>
								</eBoolean>
							</Attribute>
							<Attribute name="StartBufferOffset">
								<sFloat32>
									<Element>
										<Value>0</Value>
									</Element>
								</sFloat32>
							</Attribute>
							<Attribute name="EndBufferOffset">
								<sFloat32>
									<Element>
										<Value>0</Value>
									</Element>
								</sFloat32>
							</Attribute>
							<Attribute name="EditorOnly">
								<eBoolean>
									<Element>
										<Value>eFalse</Value>
									</Element>
								</eBoolean>
							</Attribute>
							<Attribute name="SpecialCurve">
								<kCurve-eCurveType>
									<Element>
										<Value>eInvalid</Value>
									</Element>
								</kCurve-eCurveType>
							</Attribute>
						</Value>
					</Element>
				</cSectionRenderBlueprint>
			</Attribute>
			<Attribute name="JunctionProperties">
				<cTrackSectionBlueprint-sJunctionPropertiesDesc>
					<Element>
						<Value>
							<Attribute name="CheckRailIndent">
								<sFloat32>
									<Element>
										<Value>0.15</Value>
									</Element>
								</sFloat32>
							</Attribute>
							<Attribute name="GuardRailLength">
								<sFloat32>
									<Element>
										<Value>1.5</Value>
									</Element>
								</sFloat32>
							</Attribute>
							<Attribute name="GuardRailExtLength">
								<sFloat32>
									<Element>
										<Value>0.25</Value>
									</Element>
								</sFloat32>
							</Attribute>
							<Attribute name="GuardRailExtOffset">
								<sFloat32>
									<Element>
										<Value>0.1</Value>
									</Element>
								</sFloat32>
							</Attribute>
							<Attribute name="RailWidth">
								<sFloat32>
									<Element>
										<Value>0.07</Value>
									</Element>
								</sFloat32>
							</Attribute>
							<Attribute name="SleeperPitch">
								<sFloat32>
									<Element>
										<Value>0.65</Value>
									</Element>
								</sFloat32>
							</Attribute>
							<Attribute name="SleeperHeight">
								<sFloat32>
									<Element>
										<Value>0</Value>
									</Element>
								</sFloat32>
							</Attribute>
							<Attribute name="SleeperGaugeExt">
								<sFloat32>
									<Element>
										<Value>0.45</Value>
									</Element>
								</sFloat32>
							</Attribute>
							<Attribute name="SleeperWidth">
								<sFloat32>
									<Element>
										<Value>0.15</Value>
									</Element>
								</sFloat32>
							</Attribute>
							<Attribute name="SleeperMaxLength">
								<sFloat32>
									<Element>
										<Value>4.5</Value>
									</Element>
								</sFloat32>
							</Attribute>
							<Attribute name="SleeperTextureID">
								<cDeltaString>
									<Element>
										<Value>RailNetwork\Track\textures\Concrete</Value>
									</Element>
								</cDeltaString>
							</Attribute>
							<Attribute name="SleeperTextureNormalID">
								<cDeltaString>
									<Element>
										<Value />
									</Element>
								</cDeltaString>
							</Attribute>
							<Attribute name="SleeperMinU">
								<sFloat32>
									<Element>
										<Value>0</Value>
									</Element>
								</sFloat32>
							</Attribute>
							<Attribute name="SleeperMaxU">
								<sFloat32>
									<Element>
										<Value>1</Value>
									</Element>
								</sFloat32>
							</Attribute>
							<Attribute name="SleeperMinV">
								<sFloat32>
									<Element>
										<Value>0</Value>
									</Element>
								</sFloat32>
							</Attribute>
							<Attribute name="SleeperMaxV">
								<sFloat32>
									<Element>
										<Value>1</Value>
									</Element>
								</sFloat32>
							</Attribute>
						</Value>
					</Element>
				</cTrackSectionBlueprint-sJunctionPropertiesDesc>
			</Attribute>
			<Attribute name="BedRumbleSounds">
				<__Indexed__iBlueprintLibrary-cAbsoluteBlueprintID>
					<Element>
						<Value />
					</Element>
				</__Indexed__iBlueprintLibrary-cAbsoluteBlueprintID>
			</Attribute>
			<Attribute name="DefaultBedRumbleSound">
				<iBlueprintLibrary-cAbsoluteBlueprintID>
					<Element>
						<Value>
							<Attribute name="BlueprintSetID">
								<iBlueprintLibrary-cBlueprintSetID>
									<Element>
										<Value>
											<Attribute name="Provider">
												<cDeltaString>
													<Element>
														<Value />
													</Element>
												</cDeltaString>
											</Attribute>
											<Attribute name="Product">
												<cDeltaString>
													<Element>
														<Value />
													</Element>
												</cDeltaString>
											</Attribute>
										</Value>
									</Element>
								</iBlueprintLibrary-cBlueprintSetID>
							</Attribute>
							<Attribute name="BlueprintID">
								<cDeltaString>
									<Element>
										<Value />
									</Element>
								</cDeltaString>
							</Attribute>
						</Value>
					</Element>
				</iBlueprintLibrary-cAbsoluteBlueprintID>
			</Attribute>
		</Value>
	</Element>
</cTrackSectionBlueprint>